{"actors": [{"descIndex": 0, "spawnCoords": {"x": 0, "y": 0}, "health": 60, "unk_0x24": 0, "direction": "UP", "animationType": "MobileNpc_maybe", "unk_0x28": 0, "unk_0x30": 0, "unk_0x31": 0, "unk_0x32": 0, "unk_0x34": 0, "unk_0x35": 0}, {"descIndex": 1, "spawnCoords": {"x": 54, "y": 132}, "health": 0, "unk_0x24": 0, "direction": "UP", "animationType": "UnknownType3", "unk_0x28": 0, "unk_0x30": 0, "unk_0x31": 0, "unk_0x32": 0, "unk_0x34": 0, "unk_0x35": 0}, {"descIndex": 2, "spawnCoords": {"x": 86, "y": 176}, "health": 0, "unk_0x24": 0, "direction": "UP", "animationType": "UnknownType3", "unk_0x28": 0, "unk_0x30": 0, "unk_0x31": 0, "unk_0x32": 0, "unk_0x34": 0, "unk_0x35": 0}, {"descIndex": 3, "spawnCoords": {"x": 54, "y": 202}, "health": 0, "unk_0x24": 0, "direction": "UP", "animationType": "UnknownType3", "unk_0x28": 0, "unk_0x30": 0, "unk_0x31": 0, "unk_0x32": 0, "unk_0x34": 0, "unk_0x35": 0}], "descriptions": [{"size": {"x": 56, "y": 49}, "groupCount": 2, "maxHealth_maybe": 60, "useCostOrDefense": 0, "baseDamageOrPurchasePrice_maybe": 40, "unk_0x14": 0, "unk_0x15": 0, "collisionSamplePoints": [{"x": 0, "y": 0}, {"x": 0, "y": 0}], "unk_0x24": 4, "bonusDamage": 0, "unk_0x2b": 0, "unk_0x2c": 0, "unk_0x2a": 0, "type_maybe": "UnknownType0", "weakToSpell": "None", "interactsWithItem": "NoneOrVialOfAcid", "groups": [{"animationFrameOrder": [0, 1, 2, 1], "unk_0x12": 0, "frameDelay": 4, "unk_0x18": [{"x": 0, "y": 0}, {"x": 0, "y": 0}, {"x": 0, "y": 0}], "damageSamplePoints_maybe": [{"x": 29, "y": -4}, {"x": 49, "y": 2}, {"x": 55, "y": 33}, {"x": 44, "y": 57}, {"x": 27, "y": 64}, {"x": 5, "y": 47}, {"x": 5, "y": 9}], "unknownFieldFromSpriteTree": 5493208}, {"animationFrameOrder": [0, 1, 2, 1], "unk_0x12": 0, "frameDelay": 4, "unk_0x18": [{"x": 55, "y": 12}, {"x": 55, "y": 30}, {"x": 54, "y": 54}], "damageSamplePoints_maybe": [{"x": 29, "y": 61}, {"x": 48, "y": 54}, {"x": 58, "y": 28}, {"x": 50, "y": 8}, {"x": 30, "y": -4}, {"x": 7, "y": 11}, {"x": 2, "y": 40}, {"x": 17, "y": 51}], "unknownFieldFromSpriteTree": 5496488}], "unknownFieldFromSpriteTree": 5493192, "commonName": "npc.merchant.unknownActor189"}, {"size": {"x": 32, "y": 50}, "groupCount": 2, "maxHealth_maybe": 0, "useCostOrDefense": 0, "baseDamageOrPurchasePrice_maybe": 0, "unk_0x14": 0, "unk_0x15": 0, "collisionSamplePoints": [{"x": 40, "y": 8}, {"x": 42, "y": 16}], "unk_0x24": 0, "bonusDamage": 0, "unk_0x2b": 0, "unk_0x2c": 0, "unk_0x2a": 0, "type_maybe": "UnknownType0", "weakToSpell": "None", "interactsWithItem": "NoneOrVialOfAcid", "groups": [{"animationFrameOrder": [0], "unk_0x12": 0, "frameDelay": 0, "unk_0x18": [{"x": 46, "y": -5}, {"x": 46, "y": 14}, {"x": 45, "y": 33}], "damageSamplePoints_maybe": [{"x": 60, "y": 18}, {"x": 51, "y": -8}, {"x": 37, "y": -15}, {"x": 18, "y": -6}, {"x": 15, "y": 14}, {"x": 23, "y": 36}, {"x": 42, "y": 38}, {"x": 55, "y": 31}], "unknownFieldFromSpriteTree": 5499512}, {"animationFrameOrder": [0], "unk_0x12": 0, "frameDelay": 0, "unk_0x18": [{"x": 48, "y": -4}, {"x": 46, "y": 15}, {"x": 47, "y": 38}], "damageSamplePoints_maybe": [{"x": 21, "y": 42}, {"x": 37, "y": 48}, {"x": 54, "y": 42}, {"x": 59, "y": 13}, {"x": 52, "y": -7}, {"x": 29, "y": -12}, {"x": 9, "y": 0}, {"x": 7, "y": 20}], "unknownFieldFromSpriteTree": 5500064}], "unknownFieldFromSpriteTree": 5499496, "commonName": "item.treasure.alligatorBoots"}, {"size": {"x": 32, "y": 44}, "groupCount": 2, "maxHealth_maybe": 0, "useCostOrDefense": 0, "baseDamageOrPurchasePrice_maybe": 300, "unk_0x14": 0, "unk_0x15": 0, "collisionSamplePoints": [{"x": 26, "y": 8}, {"x": 28, "y": 16}], "unk_0x24": 0, "bonusDamage": 0, "unk_0x2b": 0, "unk_0x2c": 0, "unk_0x2a": 48, "type_maybe": "UnknownType0", "weakToSpell": "None", "interactsWithItem": "NoneOrVialOfAcid", "groups": [{"animationFrameOrder": [0], "unk_0x12": 0, "frameDelay": 0, "unk_0x18": [{"x": 45, "y": -3}, {"x": 45, "y": 12}, {"x": 44, "y": 30}], "damageSamplePoints_maybe": [{"x": 3, "y": 12}, {"x": 51, "y": 13}, {"x": 46, "y": 31}, {"x": 31, "y": 35}, {"x": 17, "y": 27}, {"x": 12, "y": -5}, {"x": 25, "y": -7}, {"x": 41, "y": -7}], "unknownFieldFromSpriteTree": 5501240}, {"animationFrameOrder": [0], "unk_0x12": 0, "frameDelay": 0, "unk_0x18": [{"x": 43, "y": -5}, {"x": 43, "y": 19}, {"x": 42, "y": 43}], "damageSamplePoints_maybe": [{"x": 47, "y": -6}, {"x": 27, "y": -14}, {"x": 3, "y": -12}, {"x": -8, "y": 12}, {"x": 6, "y": 38}, {"x": 25, "y": 38}, {"x": 40, "y": 38}, {"x": 50, "y": 18}], "unknownFieldFromSpriteTree": 5501900}], "unknownFieldFromSpriteTree": 5501224, "commonName": "item.treasure.deepFriedOctorokLegs"}, {"size": {"x": 32, "y": 42}, "groupCount": 2, "maxHealth_maybe": 0, "useCostOrDefense": 0, "baseDamageOrPurchasePrice_maybe": 100, "unk_0x14": 0, "unk_0x15": 0, "collisionSamplePoints": [{"x": 40, "y": 12}, {"x": 40, "y": 16}], "unk_0x24": 0, "bonusDamage": 0, "unk_0x2b": 0, "unk_0x2c": 0, "unk_0x2a": 48, "type_maybe": "UnknownType0", "weakToSpell": "None", "interactsWithItem": "NoneOrVialOfAcid", "groups": [{"animationFrameOrder": [0], "unk_0x12": 0, "frameDelay": 0, "unk_0x18": [{"x": 39, "y": 3}, {"x": 39, "y": 16}, {"x": 39, "y": 27}], "damageSamplePoints_maybe": [{"x": 32, "y": 40}, {"x": 46, "y": 37}, {"x": 53, "y": 20}, {"x": 50, "y": 0}, {"x": 36, "y": -10}, {"x": 15, "y": -8}, {"x": -2, "y": 7}, {"x": 10, "y": 30}], "unknownFieldFromSpriteTree": 5503124}, {"animationFrameOrder": [0], "unk_0x12": 0, "frameDelay": 0, "unk_0x18": [{"x": 45, "y": 1}, {"x": 45, "y": 14}, {"x": 45, "y": 28}], "damageSamplePoints_maybe": [{"x": 30, "y": 42}, {"x": 31, "y": -11}, {"x": 52, "y": 17}, {"x": 46, "y": 38}, {"x": 47, "y": -5}, {"x": 10, "y": -6}, {"x": -3, "y": 14}, {"x": 9, "y": 34}], "unknownFieldFromSpriteTree": 5503832}], "unknownFieldFromSpriteTree": 5503108, "commonName": "item.treasure.repellent"}]}