{"actors": [{"descIndex": 0, "spawnCoords": {"x": 152, "y": 216}, "health": 60, "unk_0x24": 0, "direction": "UP", "animationType": "UnknownType2", "unk_0x28": 0, "unk_0x30": 0, "unk_0x31": 0, "unk_0x32": 0, "unk_0x34": 0, "unk_0x35": 0}, {"descIndex": 0, "spawnCoords": {"x": 124, "y": 138}, "health": 60, "unk_0x24": 0, "direction": "UP", "animationType": "UnknownType2", "unk_0x28": 0, "unk_0x30": 0, "unk_0x31": 0, "unk_0x32": 0, "unk_0x34": 0, "unk_0x35": 0}], "descriptions": [{"size": {"x": 60, "y": 56}, "groupCount": 4, "maxHealth_maybe": 60, "useCostOrDefense": 30, "baseDamageOrPurchasePrice_maybe": 73, "unk_0x14": 0, "unk_0x15": 0, "collisionSamplePoints": [{"x": 35, "y": 16}, {"x": 34, "y": 26}], "unk_0x24": 4, "bonusDamage": 0, "unk_0x2b": 0, "unk_0x2c": 0, "unk_0x2a": 0, "type_maybe": "UnknownType1_CanDamage", "weakToSpell": "None", "interactsWithItem": "NoneOrVialOfAcid", "groups": [{"animationFrameOrder": [0, 1, 2, 3, 4, 3, 2, 1], "unk_0x12": 0, "frameDelay": 3, "unk_0x18": [{"x": 59, "y": 5}, {"x": 59, "y": 32}, {"x": 58, "y": 56}], "damageSamplePoints_maybe": [{"x": 0, "y": 27}, {"x": 7, "y": 49}, {"x": 27, "y": 50}, {"x": 47, "y": 43}, {"x": 57, "y": 29}, {"x": 45, "y": 16}, {"x": 29, "y": 12}, {"x": 12, "y": 10}], "unknownFieldFromSpriteTree": 5491408}, {"animationFrameOrder": [0, 1, 2, 3, 4, 3, 2, 1], "unk_0x12": 0, "frameDelay": 3, "unk_0x18": [{"x": 52, "y": -2}, {"x": 53, "y": 25}, {"x": 51, "y": 50}], "damageSamplePoints_maybe": [{"x": 5, "y": 18}, {"x": 9, "y": 37}, {"x": 19, "y": 56}, {"x": 39, "y": 53}, {"x": 48, "y": 40}, {"x": 50, "y": 13}, {"x": 34, "y": 4}, {"x": 15, "y": 3}], "unknownFieldFromSpriteTree": 5499144}, {"animationFrameOrder": [0, 1, 2, 3, 4, 3, 2, 1], "unk_0x12": 0, "frameDelay": 3, "unk_0x18": [{"x": 48, "y": -2}, {"x": 49, "y": 28}, {"x": 47, "y": 56}], "damageSamplePoints_maybe": [{"x": 3, "y": 28}, {"x": 12, "y": 46}, {"x": 29, "y": 54}, {"x": 46, "y": 50}, {"x": 51, "y": 28}, {"x": 44, "y": 8}, {"x": 25, "y": 3}, {"x": 8, "y": 10}], "unknownFieldFromSpriteTree": 5506396}, {"animationFrameOrder": [0, 1, 2, 3, 4, 3, 2, 1], "unk_0x12": 0, "frameDelay": 3, "unk_0x18": [{"x": 52, "y": -3}, {"x": 52, "y": 28}, {"x": 50, "y": 59}], "damageSamplePoints_maybe": [{"x": 6, "y": 33}, {"x": 16, "y": 56}, {"x": 34, "y": 56}, {"x": 51, "y": 44}, {"x": 53, "y": 20}, {"x": 39, "y": 8}, {"x": 14, "y": 8}], "unknownFieldFromSpriteTree": 5514336}], "unknownFieldFromSpriteTree": 5491384, "commonName": "enemy.gibdo"}]}